ischedule/__init__.py
ischedule/ischedule.py
ischedule/py.typed
ischedule-1.2.7.dist-info/METADATA
ischedule-1.2.7.dist-info/WHEEL
ischedule-1.2.7.dist-info/top_level.txt
ischedule-1.2.7.dist-info/RECORD
