Metadata-Version: 2.1
Name: ischedule
Version: 1.2.7
Summary: Single-thread interval scheduler
Home-page: https://github.com/aleksve/ischedule
Author: Aleksander Veksler
Author-email: aleksve@gmail.com
Project-URL: Bug Tracker, https://github.com/aleksve/ischedule/issues
Classifier: Programming Language :: Python :: 3
Classifier: License :: OSI Approved :: MIT License
Classifier: Operating System :: OS Independent
Requires-Python: >=3.7
